composapy/__init__.py
composapy/api.py
composapy/auth.py
composapy/bindings.py
composapy/config.py
composapy/decorators.py
composapy/loader.py
composapy/magics.py
composapy/mixins.py
composapy/session.py
composapy/stream.py
composapy/testdlls.py
composapy/utils.py
composapy/dataflow/__init__.py
composapy/dataflow/api.py
composapy/dataflow/const.py
composapy/dataflow/io.py
composapy/dataflow/models.py
composapy/interactive/__init__.py
composapy/interactive/itable.py
composapy/interactive/options.py
composapy/key/__init__.py
composapy/key/api.py
composapy/key/models.py
composapy/notebook/__init__.py
composapy/notebook/inject.py
composapy/notebook/nb_wrap.py
composapy/notebook/nbr_globals.py
composapy/notebook/script_wrap.py
composapy/patch/__init__.py
composapy/patch/execution_handle.py
composapy/patch/file_reference.py
composapy/patch/queryview.py
composapy/patch/table.py
composapy/queryview/__init__.py
composapy/queryview/api.py
composapy/queryview/const.py
composapy/queryview/models.py
composapy/static/datatables_template.html
tests/__init__.py
tests/conftest.py
tests/test_api.py
tests/test_key.py
tests/test_loader.py
tests/test_models.py
tests/test_queryview.py
tests/test_session.py
tests/test_windows_auth.py
composapy-0.13.3.dist-info/LICENSE
composapy-0.13.3.dist-info/METADATA
composapy-0.13.3.dist-info/WHEEL
composapy-0.13.3.dist-info/top_level.txt
composapy-0.13.3.dist-info/RECORD
