Metadata-Version: 2.1
Name: composapy
Version: 0.13.3
Summary: ComposableAnalytics csharp binding for python
Home-page: https://github.com/ComposableAnalytics/Composapy
Author: Composable
Author-email: support@composableanalytics.com
Project-URL: Bug Tracker, https://github.com/ComposableAnalytics/Composapy/issues
Classifier: Programming Language :: Python :: 3
Classifier: License :: OSI Approved :: MIT License
Classifier: Operating System :: OS Independent
Requires-Python: >=3.7.1
License-File: LICENSE
Provides-Extra: deps
Requires-Dist: pythonnet==3.0.1; extra == "deps"
Requires-Dist: clr-loader==0.2.5; extra == "deps"
Requires-Dist: numpy<=1.25.0; extra == "deps"
Requires-Dist: pandas<=2.0.3; extra == "deps"
Requires-Dist: papermill; extra == "deps"
Requires-Dist: json-fix; extra == "deps"
